Workbook

Sheet Start Here
B1: UK Etsy Seller Profit Tracker
B2: Real profit per sale and per product after every Etsy fee, plus a VAT threshold check.
B4: SET UP IN 3 STEPS
B5: 1. Go to Settings. Type your shop name, say whether you have given Etsy a VAT number, and check the fee rates.
B6: 2. Add your products on Products (SKU, name, cost per unit).
B7: 3. Add each sale on Sales and other costs on Expenses. Type only in the cream cells.
B9: WHAT YOU SEE
B10: • Sales works out Etsy's fees, VAT on fees, cost of goods and profit for every line.
B11: • Profit per Product shows which products make money. Monthly Summary shows your year, and checks the £90,000 VAT threshold.
B12: • An order with two products: one row each, the same order number, and postage on the first row. The 20p fee is counted once.
B13: • Grey cells hold formulas and are protected without a password (Review > Unprotect Sheet to change them).
B14: • Works in Excel, Google Sheets (File > Import), Apple Numbers and LibreOffice. No macros.
... B19: This is a record-keeping tool, not tax advice. For your tax return totals, use the Sole Trader Quarterly Tracker or your accountant.

Sheet Settings
B1: Settings
B2: Fill in the cream cells once. Check the fee rates against Etsy's fee page each year.
G3: Dropdown lists
B4: Shop name | C4: Your shop name | G4: Cost of goods bought for resale or goods used | J4: Yes
B5: Given Etsy a UK VAT number? | C5: No | D5: If Yes, Etsy doesn't charge VAT on your fees. | G5: Construction industry - payments to subcontractors | J5: No
B6: First month of your year | C6: 46113 | D6: The Monthly Summary starts here. | G6: Wages, salaries and other staff costs
B7: VAT check as at | D7: Leave blank to use today's date. | G7: Car, van and travel expenses
B8: VAT check date in use | C8: =IF(C7="",TODAY(),C7) | G8: Rent, rates, power and insurance costs
G9: Repairs and maintenance of property and equipment
B10: Etsy fee | C10: Rate | D10: Etsy UK rates as published June 2026 | G10: Phone, fax, stationery and other office costs
B11: Transaction fee (% of item price + postage) | C11: 0.065 | G11: Advertising and business entertainment costs
B12: Payment processing (% of order total) | C12: 0.04 | G12: Interest on bank and other loans
B13: Payment processing (fixed, per order) | C13: 0.2 | G13: Bank, credit card and other financial charges
B14: Regulatory operating fee (% of item price + postage) | C14: 0.0048 | G14: Irrecoverable debts written off
B15: Listing renewal (per item sold, about $0.20) | C15: 0.16 | G15: Accountancy, legal and other professional fees
B16: Offsite Ads (% of order, when a sale came from an ad) | C16: 0.15 | G16: Depreciation and loss or profit on sale of assets
B17: VAT on Etsy fees (if you haven't given Etsy a VAT number) | C17: 0.2 | G17: Other business expenses
B19: VAT registration threshold £ | C19: 90000
B20: If Etsy changes a rate, update it at the start of a new year or start a fresh copy, so past sales keep their rates.

Sheet Products
B1: Products
B2: One row per product. Costs are per unit.
B4: SKU | C4: Product name | D4: Materials £ per unit | E4: Packaging £ per unit | F4: Unit cost £
F5: =IF(B5="","",D5+E5)
F6: =IF(B6="","",D6+E6)
F7: =IF(B7="","",D7+E7)
F8: =IF(B8="","",D8+E8)
F9: =IF(B9="","",D9+E9)
F10: =IF(B10="","",D10+E10)
F11: =IF(B11="","",D11+E11)
F12: =IF(B12="","",D12+E12)
F13: =IF(B13="","",D13+E13)
F14: =IF(B14="","",D14+E14)
F15: =IF(B15="","",D15+E15)
F16: =IF(B16="","",D16+E16)
... F204: =IF(B204="","",D204+E204)

Sheet Sales
B1: Sales
B2: One row per product in each order. Copy the figures from your Etsy order.
B4: Date | C4: Order no. | D4: SKU | E4: Qty | F4: Item price £ | G4: Postage charged £ | H4: From Offsite Ad? | I4: Postage you paid £ | J4: Revenue £ | K4: Etsy fees £ | L4: VAT on fees £ | M4: Cost of goods £ | N4: Profit £
J5: =IF(B5="","",F5+G5) | K5: =IF(B5="","",J5*(Settings!$C$11+Settings!$C$12+Settings!$C$14)+IF(C5="",Settings!$C$13,IF(COUNTIF($C$5:C5,C5)=1,Settings!$C$13,0))+E5*Settings!$C$15+IF(H5="Yes",J5*Settings!$C$16,0)) | L5: =IF(B5="","",IF(Settings!$C$5="Yes",0,K5*Settings!$C$17)) | M5: =IF(B5="","",E5*IFERROR(VLOOKUP(D5,Products!$B$5:$F$204,5,FALSE),0)) | N5: =IF(B5="","",J5-K5-L5-M5-I5)
J6: =IF(B6="","",F6+G6) | K6: =IF(B6="","",J6*(Settings!$C$11+Settings!$C$12+Settings!$C$14)+IF(C6="",Settings!$C$13,IF(COUNTIF($C$5:C6,C6)=1,Settings!$C$13,0))+E6*Settings!$C$15+IF(H6="Yes",J6*Settings!$C$16,0)) | L6: =IF(B6="","",IF(Settings!$C$5="Yes",0,K6*Settings!$C$17)) | M6: =IF(B6="","",E6*IFERROR(VLOOKUP(D6,Products!$B$5:$F$204,5,FALSE),0)) | N6: =IF(B6="","",J6-K6-L6-M6-I6)
J7: =IF(B7="","",F7+G7) | K7: =IF(B7="","",J7*(Settings!$C$11+Settings!$C$12+Settings!$C$14)+IF(C7="",Settings!$C$13,IF(COUNTIF($C$5:C7,C7)=1,Settings!$C$13,0))+E7*Settings!$C$15+IF(H7="Yes",J7*Settings!$C$16,0)) | L7: =IF(B7="","",IF(Settings!$C$5="Yes",0,K7*Settings!$C$17)) | M7: =IF(B7="","",E7*IFERROR(VLOOKUP(D7,Products!$B$5:$F$204,5,FALSE),0)) | N7: =IF(B7="","",J7-K7-L7-M7-I7)
J8: =IF(B8="","",F8+G8) | K8: =IF(B8="","",J8*(Settings!$C$11+Settings!$C$12+Settings!$C$14)+IF(C8="",Settings!$C$13,IF(COUNTIF($C$5:C8,C8)=1,Settings!$C$13,0))+E8*Settings!$C$15+IF(H8="Yes",J8*Settings!$C$16,0)) | L8: =IF(B8="","",IF(Settings!$C$5="Yes",0,K8*Settings!$C$17)) | M8: =IF(B8="","",E8*IFERROR(VLOOKUP(D8,Products!$B$5:$F$204,5,FALSE),0)) | N8: =IF(B8="","",J8-K8-L8-M8-I8)
J9: =IF(B9="","",F9+G9) | K9: =IF(B9="","",J9*(Settings!$C$11+Settings!$C$12+Settings!$C$14)+IF(C9="",Settings!$C$13,IF(COUNTIF($C$5:C9,C9)=1,Settings!$C$13,0))+E9*Settings!$C$15+IF(H9="Yes",J9*Settings!$C$16,0)) | L9: =IF(B9="","",IF(Settings!$C$5="Yes",0,K9*Settings!$C$17)) | M9: =IF(B9="","",E9*IFERROR(VLOOKUP(D9,Products!$B$5:$F$204,5,FALSE),0)) | N9: =IF(B9="","",J9-K9-L9-M9-I9)
J10: =IF(B10="","",F10+G10) | K10: =IF(B10="","",J10*(Settings!$C$11+Settings!$C$12+Settings!$C$14)+IF(C10="",Settings!$C$13,IF(COUNTIF($C$5:C10,C10)=1,Settings!$C$13,0))+E10*Settings!$C$15+IF(H10="Yes",J10*Settings!$C$16,0)) | L10: =IF(B10="","",IF(Settings!$C$5="Yes",0,K10*Settings!$C$17)) | M10: =IF(B10="","",E10*IFERROR(VLOOKUP(D10,Products!$B$5:$F$204,5,FALSE),0)) | N10: =IF(B10="","",J10-K10-L10-M10-I10)
J11: =IF(B11="","",F11+G11) | K11: =IF(B11="","",J11*(Settings!$C$11+Settings!$C$12+Settings!$C$14)+IF(C11="",Settings!$C$13,IF(COUNTIF($C$5:C11,C11)=1,Settings!$C$13,0))+E11*Settings!$C$15+IF(H11="Yes",J11*Settings!$C$16,0)) | L11: =IF(B11="","",IF(Settings!$C$5="Yes",0,K11*Settings!$C$17)) | M11: =IF(B11="","",E11*IFERROR(VLOOKUP(D11,Products!$B$5:$F$204,5,FALSE),0)) | N11: =IF(B11="","",J11-K11-L11-M11-I11)
J12: =IF(B12="","",F12+G12) | K12: =IF(B12="","",J12*(Settings!$C$11+Settings!$C$12+Settings!$C$14)+IF(C12="",Settings!$C$13,IF(COUNTIF($C$5:C12,C12)=1,Settings!$C$13,0))+E12*Settings!$C$15+IF(H12="Yes",J12*Settings!$C$16,0)) | L12: =IF(B12="","",IF(Settings!$C$5="Yes",0,K12*Settings!$C$17)) | M12: =IF(B12="","",E12*IFERROR(VLOOKUP(D12,Products!$B$5:$F$204,5,FALSE),0)) | N12: =IF(B12="","",J12-K12-L12-M12-I12)
J13: =IF(B13="","",F13+G13) | K13: =IF(B13="","",J13*(Settings!$C$11+Settings!$C$12+Settings!$C$14)+IF(C13="",Settings!$C$13,IF(COUNTIF($C$5:C13,C13)=1,Settings!$C$13,0))+E13*Settings!$C$15+IF(H13="Yes",J13*Settings!$C$16,0)) | L13: =IF(B13="","",IF(Settings!$C$5="Yes",0,K13*Settings!$C$17)) | M13: =IF(B13="","",E13*IFERROR(VLOOKUP(D13,Products!$B$5:$F$204,5,FALSE),0)) | N13: =IF(B13="","",J13-K13-L13-M13-I13)
J14: =IF(B14="","",F14+G14) | K14: =IF(B14="","",J14*(Settings!$C$11+Settings!$C$12+Settings!$C$14)+IF(C14="",Settings!$C$13,IF(COUNTIF($C$5:C14,C14)=1,Settings!$C$13,0))+E14*Settings!$C$15+IF(H14="Yes",J14*Settings!$C$16,0)) | L14: =IF(B14="","",IF(Settings!$C$5="Yes",0,K14*Settings!$C$17)) | M14: =IF(B14="","",E14*IFERROR(VLOOKUP(D14,Products!$B$5:$F$204,5,FALSE),0)) | N14: =IF(B14="","",J14-K14-L14-M14-I14)
J15: =IF(B15="","",F15+G15) | K15: =IF(B15="","",J15*(Settings!$C$11+Settings!$C$12+Settings!$C$14)+IF(C15="",Settings!$C$13,IF(COUNTIF($C$5:C15,C15)=1,Settings!$C$13,0))+E15*Settings!$C$15+IF(H15="Yes",J15*Settings!$C$16,0)) | L15: =IF(B15="","",IF(Settings!$C$5="Yes",0,K15*Settings!$C$17)) | M15: =IF(B15="","",E15*IFERROR(VLOOKUP(D15,Products!$B$5:$F$204,5,FALSE),0)) | N15: =IF(B15="","",J15-K15-L15-M15-I15)
J16: =IF(B16="","",F16+G16) | K16: =IF(B16="","",J16*(Settings!$C$11+Settings!$C$12+Settings!$C$14)+IF(C16="",Settings!$C$13,IF(COUNTIF($C$5:C16,C16)=1,Settings!$C$13,0))+E16*Settings!$C$15+IF(H16="Yes",J16*Settings!$C$16,0)) | L16: =IF(B16="","",IF(Settings!$C$5="Yes",0,K16*Settings!$C$17)) | M16: =IF(B16="","",E16*IFERROR(VLOOKUP(D16,Products!$B$5:$F$204,5,FALSE),0)) | N16: =IF(B16="","",J16-K16-L16-M16-I16)
... J2004: =IF(B2004="","",F2004+G2004) | K2004: =IF(B2004="","",J2004*(Settings!$C$11+Settings!$C$12+Settings!$C$14)+IF(C2004="",Settings!$C$13,IF(COUNTIF($C$5:C2004,C2004)=1,Settings!$C$13,0))+E2004*Settings!$C$15+IF(H2004="Yes",J2004*Settings!$C$16,0)) | L2004: =IF(B2004="","",IF(Settings!$C$5="Yes",0,K2004*Settings!$C$17)) | M2004: =IF(B2004="","",E2004*IFERROR(VLOOKUP(D2004,Products!$B$5:$F$204,5,FALSE),0)) | N2004: =IF(B2004="","",J2004-K2004-L2004-M2004-I2004)

Sheet Expenses
B1: Expenses
B2: Other business costs: Etsy Ads, supplies in bulk, software, insurance.
B4: Date | C4: Supplier | D4: Description | E4: Category | F4: Amount £ | G4: Ref

Sheet Profit per Product
B1: Profit per Product
B2: Which products earn their keep. Nothing to type here.
B4: SKU | C4: Product | D4: Units sold | E4: Revenue £ | F4: Fees and VAT £ | G4: Cost of goods £ | H4: Postage paid £ | I4: Profit £ | J4: Profit margin
B5: =IF(Products!B5="","",Products!B5) | C5: =IF(B5="","",Products!C5) | D5: =IF(B5="","",SUMIFS(Sales!$E$5:$E$2004,Sales!$D$5:$D$2004,B5)) | E5: =IF(B5="","",SUMIFS(Sales!$J$5:$J$2004,Sales!$D$5:$D$2004,B5)) | F5: =IF(B5="","",SUMIFS(Sales!$K$5:$K$2004,Sales!$D$5:$D$2004,B5)+SUMIFS(Sales!$L$5:$L$2004,Sales!$D$5:$D$2004,B5)) | G5: =IF(B5="","",SUMIFS(Sales!$M$5:$M$2004,Sales!$D$5:$D$2004,B5)) | H5: =IF(B5="","",SUMIFS(Sales!$I$5:$I$2004,Sales!$D$5:$D$2004,B5)) | I5: =IF(B5="","",E5-F5-G5-H5) | J5: =IF(B5="","",IF(E5=0,"",I5/E5))
B6: =IF(Products!B6="","",Products!B6) | C6: =IF(B6="","",Products!C6) | D6: =IF(B6="","",SUMIFS(Sales!$E$5:$E$2004,Sales!$D$5:$D$2004,B6)) | E6: =IF(B6="","",SUMIFS(Sales!$J$5:$J$2004,Sales!$D$5:$D$2004,B6)) | F6: =IF(B6="","",SUMIFS(Sales!$K$5:$K$2004,Sales!$D$5:$D$2004,B6)+SUMIFS(Sales!$L$5:$L$2004,Sales!$D$5:$D$2004,B6)) | G6: =IF(B6="","",SUMIFS(Sales!$M$5:$M$2004,Sales!$D$5:$D$2004,B6)) | H6: =IF(B6="","",SUMIFS(Sales!$I$5:$I$2004,Sales!$D$5:$D$2004,B6)) | I6: =IF(B6="","",E6-F6-G6-H6) | J6: =IF(B6="","",IF(E6=0,"",I6/E6))
B7: =IF(Products!B7="","",Products!B7) | C7: =IF(B7="","",Products!C7) | D7: =IF(B7="","",SUMIFS(Sales!$E$5:$E$2004,Sales!$D$5:$D$2004,B7)) | E7: =IF(B7="","",SUMIFS(Sales!$J$5:$J$2004,Sales!$D$5:$D$2004,B7)) | F7: =IF(B7="","",SUMIFS(Sales!$K$5:$K$2004,Sales!$D$5:$D$2004,B7)+SUMIFS(Sales!$L$5:$L$2004,Sales!$D$5:$D$2004,B7)) | G7: =IF(B7="","",SUMIFS(Sales!$M$5:$M$2004,Sales!$D$5:$D$2004,B7)) | H7: =IF(B7="","",SUMIFS(Sales!$I$5:$I$2004,Sales!$D$5:$D$2004,B7)) | I7: =IF(B7="","",E7-F7-G7-H7) | J7: =IF(B7="","",IF(E7=0,"",I7/E7))
B8: =IF(Products!B8="","",Products!B8) | C8: =IF(B8="","",Products!C8) | D8: =IF(B8="","",SUMIFS(Sales!$E$5:$E$2004,Sales!$D$5:$D$2004,B8)) | E8: =IF(B8="","",SUMIFS(Sales!$J$5:$J$2004,Sales!$D$5:$D$2004,B8)) | F8: =IF(B8="","",SUMIFS(Sales!$K$5:$K$2004,Sales!$D$5:$D$2004,B8)+SUMIFS(Sales!$L$5:$L$2004,Sales!$D$5:$D$2004,B8)) | G8: =IF(B8="","",SUMIFS(Sales!$M$5:$M$2004,Sales!$D$5:$D$2004,B8)) | H8: =IF(B8="","",SUMIFS(Sales!$I$5:$I$2004,Sales!$D$5:$D$2004,B8)) | I8: =IF(B8="","",E8-F8-G8-H8) | J8: =IF(B8="","",IF(E8=0,"",I8/E8))
B9: =IF(Products!B9="","",Products!B9) | C9: =IF(B9="","",Products!C9) | D9: =IF(B9="","",SUMIFS(Sales!$E$5:$E$2004,Sales!$D$5:$D$2004,B9)) | E9: =IF(B9="","",SUMIFS(Sales!$J$5:$J$2004,Sales!$D$5:$D$2004,B9)) | F9: =IF(B9="","",SUMIFS(Sales!$K$5:$K$2004,Sales!$D$5:$D$2004,B9)+SUMIFS(Sales!$L$5:$L$2004,Sales!$D$5:$D$2004,B9)) | G9: =IF(B9="","",SUMIFS(Sales!$M$5:$M$2004,Sales!$D$5:$D$2004,B9)) | H9: =IF(B9="","",SUMIFS(Sales!$I$5:$I$2004,Sales!$D$5:$D$2004,B9)) | I9: =IF(B9="","",E9-F9-G9-H9) | J9: =IF(B9="","",IF(E9=0,"",I9/E9))
B10: =IF(Products!B10="","",Products!B10) | C10: =IF(B10="","",Products!C10) | D10: =IF(B10="","",SUMIFS(Sales!$E$5:$E$2004,Sales!$D$5:$D$2004,B10)) | E10: =IF(B10="","",SUMIFS(Sales!$J$5:$J$2004,Sales!$D$5:$D$2004,B10)) | F10: =IF(B10="","",SUMIFS(Sales!$K$5:$K$2004,Sales!$D$5:$D$2004,B10)+SUMIFS(Sales!$L$5:$L$2004,Sales!$D$5:$D$2004,B10)) | G10: =IF(B10="","",SUMIFS(Sales!$M$5:$M$2004,Sales!$D$5:$D$2004,B10)) | H10: =IF(B10="","",SUMIFS(Sales!$I$5:$I$2004,Sales!$D$5:$D$2004,B10)) | I10: =IF(B10="","",E10-F10-G10-H10) | J10: =IF(B10="","",IF(E10=0,"",I10/E10))
B11: =IF(Products!B11="","",Products!B11) | C11: =IF(B11="","",Products!C11) | D11: =IF(B11="","",SUMIFS(Sales!$E$5:$E$2004,Sales!$D$5:$D$2004,B11)) | E11: =IF(B11="","",SUMIFS(Sales!$J$5:$J$2004,Sales!$D$5:$D$2004,B11)) | F11: =IF(B11="","",SUMIFS(Sales!$K$5:$K$2004,Sales!$D$5:$D$2004,B11)+SUMIFS(Sales!$L$5:$L$2004,Sales!$D$5:$D$2004,B11)) | G11: =IF(B11="","",SUMIFS(Sales!$M$5:$M$2004,Sales!$D$5:$D$2004,B11)) | H11: =IF(B11="","",SUMIFS(Sales!$I$5:$I$2004,Sales!$D$5:$D$2004,B11)) | I11: =IF(B11="","",E11-F11-G11-H11) | J11: =IF(B11="","",IF(E11=0,"",I11/E11))
B12: =IF(Products!B12="","",Products!B12) | C12: =IF(B12="","",Products!C12) | D12: =IF(B12="","",SUMIFS(Sales!$E$5:$E$2004,Sales!$D$5:$D$2004,B12)) | E12: =IF(B12="","",SUMIFS(Sales!$J$5:$J$2004,Sales!$D$5:$D$2004,B12)) | F12: =IF(B12="","",SUMIFS(Sales!$K$5:$K$2004,Sales!$D$5:$D$2004,B12)+SUMIFS(Sales!$L$5:$L$2004,Sales!$D$5:$D$2004,B12)) | G12: =IF(B12="","",SUMIFS(Sales!$M$5:$M$2004,Sales!$D$5:$D$2004,B12)) | H12: =IF(B12="","",SUMIFS(Sales!$I$5:$I$2004,Sales!$D$5:$D$2004,B12)) | I12: =IF(B12="","",E12-F12-G12-H12) | J12: =IF(B12="","",IF(E12=0,"",I12/E12))
B13: =IF(Products!B13="","",Products!B13) | C13: =IF(B13="","",Products!C13) | D13: =IF(B13="","",SUMIFS(Sales!$E$5:$E$2004,Sales!$D$5:$D$2004,B13)) | E13: =IF(B13="","",SUMIFS(Sales!$J$5:$J$2004,Sales!$D$5:$D$2004,B13)) | F13: =IF(B13="","",SUMIFS(Sales!$K$5:$K$2004,Sales!$D$5:$D$2004,B13)+SUMIFS(Sales!$L$5:$L$2004,Sales!$D$5:$D$2004,B13)) | G13: =IF(B13="","",SUMIFS(Sales!$M$5:$M$2004,Sales!$D$5:$D$2004,B13)) | H13: =IF(B13="","",SUMIFS(Sales!$I$5:$I$2004,Sales!$D$5:$D$2004,B13)) | I13: =IF(B13="","",E13-F13-G13-H13) | J13: =IF(B13="","",IF(E13=0,"",I13/E13))
B14: =IF(Products!B14="","",Products!B14) | C14: =IF(B14="","",Products!C14) | D14: =IF(B14="","",SUMIFS(Sales!$E$5:$E$2004,Sales!$D$5:$D$2004,B14)) | E14: =IF(B14="","",SUMIFS(Sales!$J$5:$J$2004,Sales!$D$5:$D$2004,B14)) | F14: =IF(B14="","",SUMIFS(Sales!$K$5:$K$2004,Sales!$D$5:$D$2004,B14)+SUMIFS(Sales!$L$5:$L$2004,Sales!$D$5:$D$2004,B14)) | G14: =IF(B14="","",SUMIFS(Sales!$M$5:$M$2004,Sales!$D$5:$D$2004,B14)) | H14: =IF(B14="","",SUMIFS(Sales!$I$5:$I$2004,Sales!$D$5:$D$2004,B14)) | I14: =IF(B14="","",E14-F14-G14-H14) | J14: =IF(B14="","",IF(E14=0,"",I14/E14))
B15: =IF(Products!B15="","",Products!B15) | C15: =IF(B15="","",Products!C15) | D15: =IF(B15="","",SUMIFS(Sales!$E$5:$E$2004,Sales!$D$5:$D$2004,B15)) | E15: =IF(B15="","",SUMIFS(Sales!$J$5:$J$2004,Sales!$D$5:$D$2004,B15)) | F15: =IF(B15="","",SUMIFS(Sales!$K$5:$K$2004,Sales!$D$5:$D$2004,B15)+SUMIFS(Sales!$L$5:$L$2004,Sales!$D$5:$D$2004,B15)) | G15: =IF(B15="","",SUMIFS(Sales!$M$5:$M$2004,Sales!$D$5:$D$2004,B15)) | H15: =IF(B15="","",SUMIFS(Sales!$I$5:$I$2004,Sales!$D$5:$D$2004,B15)) | I15: =IF(B15="","",E15-F15-G15-H15) | J15: =IF(B15="","",IF(E15=0,"",I15/E15))
B16: =IF(Products!B16="","",Products!B16) | C16: =IF(B16="","",Products!C16) | D16: =IF(B16="","",SUMIFS(Sales!$E$5:$E$2004,Sales!$D$5:$D$2004,B16)) | E16: =IF(B16="","",SUMIFS(Sales!$J$5:$J$2004,Sales!$D$5:$D$2004,B16)) | F16: =IF(B16="","",SUMIFS(Sales!$K$5:$K$2004,Sales!$D$5:$D$2004,B16)+SUMIFS(Sales!$L$5:$L$2004,Sales!$D$5:$D$2004,B16)) | G16: =IF(B16="","",SUMIFS(Sales!$M$5:$M$2004,Sales!$D$5:$D$2004,B16)) | H16: =IF(B16="","",SUMIFS(Sales!$I$5:$I$2004,Sales!$D$5:$D$2004,B16)) | I16: =IF(B16="","",E16-F16-G16-H16) | J16: =IF(B16="","",IF(E16=0,"",I16/E16))
... B204: =IF(Products!B204="","",Products!B204) | C204: =IF(B204="","",Products!C204) | D204: =IF(B204="","",SUMIFS(Sales!$E$5:$E$2004,Sales!$D$5:$D$2004,B204)) | E204: =IF(B204="","",SUMIFS(Sales!$J$5:$J$2004,Sales!$D$5:$D$2004,B204)) | F204: =IF(B204="","",SUMIFS(Sales!$K$5:$K$2004,Sales!$D$5:$D$2004,B204)+SUMIFS(Sales!$L$5:$L$2004,Sales!$D$5:$D$2004,B204)) | G204: =IF(B204="","",SUMIFS(Sales!$M$5:$M$2004,Sales!$D$5:$D$2004,B204)) | H204: =IF(B204="","",SUMIFS(Sales!$I$5:$I$2004,Sales!$D$5:$D$2004,B204)) | I204: =IF(B204="","",E204-F204-G204-H204) | J204: =IF(B204="","",IF(E204=0,"",I204/E204))

Sheet Monthly Summary
B1: Monthly Summary
B2: Your shop month by month, and the VAT threshold check. Nothing to type here.
B3: =Settings!C4
B5: Month | C5: Order lines | D5: Revenue £ | E5: Etsy fees £ | F5: VAT on fees £ | G5: Cost of goods £ | H5: Postage paid £ | I5: Other expenses £ | J5: Profit £
B6: =EDATE(Settings!$C$6,0) | C6: =COUNTIFS(Sales!$B$5:$B$2004,">="&$B6,Sales!$B$5:$B$2004,"<"&EDATE($B6,1)) | D6: =SUMIFS(Sales!$J$5:$J$2004,Sales!$B$5:$B$2004,">="&$B6,Sales!$B$5:$B$2004,"<"&EDATE($B6,1)) | E6: =SUMIFS(Sales!$K$5:$K$2004,Sales!$B$5:$B$2004,">="&$B6,Sales!$B$5:$B$2004,"<"&EDATE($B6,1)) | F6: =SUMIFS(Sales!$L$5:$L$2004,Sales!$B$5:$B$2004,">="&$B6,Sales!$B$5:$B$2004,"<"&EDATE($B6,1)) | G6: =SUMIFS(Sales!$M$5:$M$2004,Sales!$B$5:$B$2004,">="&$B6,Sales!$B$5:$B$2004,"<"&EDATE($B6,1)) | H6: =SUMIFS(Sales!$I$5:$I$2004,Sales!$B$5:$B$2004,">="&$B6,Sales!$B$5:$B$2004,"<"&EDATE($B6,1)) | I6: =SUMIFS(Expenses!$F$5:$F$2004,Expenses!$B$5:$B$2004,">="&$B6,Expenses!$B$5:$B$2004,"<"&EDATE($B6,1)) | J6: =D6-E6-F6-G6-H6-I6
B7: =EDATE(Settings!$C$6,1) | C7: =COUNTIFS(Sales!$B$5:$B$2004,">="&$B7,Sales!$B$5:$B$2004,"<"&EDATE($B7,1)) | D7: =SUMIFS(Sales!$J$5:$J$2004,Sales!$B$5:$B$2004,">="&$B7,Sales!$B$5:$B$2004,"<"&EDATE($B7,1)) | E7: =SUMIFS(Sales!$K$5:$K$2004,Sales!$B$5:$B$2004,">="&$B7,Sales!$B$5:$B$2004,"<"&EDATE($B7,1)) | F7: =SUMIFS(Sales!$L$5:$L$2004,Sales!$B$5:$B$2004,">="&$B7,Sales!$B$5:$B$2004,"<"&EDATE($B7,1)) | G7: =SUMIFS(Sales!$M$5:$M$2004,Sales!$B$5:$B$2004,">="&$B7,Sales!$B$5:$B$2004,"<"&EDATE($B7,1)) | H7: =SUMIFS(Sales!$I$5:$I$2004,Sales!$B$5:$B$2004,">="&$B7,Sales!$B$5:$B$2004,"<"&EDATE($B7,1)) | I7: =SUMIFS(Expenses!$F$5:$F$2004,Expenses!$B$5:$B$2004,">="&$B7,Expenses!$B$5:$B$2004,"<"&EDATE($B7,1)) | J7: =D7-E7-F7-G7-H7-I7
B8: =EDATE(Settings!$C$6,2) | C8: =COUNTIFS(Sales!$B$5:$B$2004,">="&$B8,Sales!$B$5:$B$2004,"<"&EDATE($B8,1)) | D8: =SUMIFS(Sales!$J$5:$J$2004,Sales!$B$5:$B$2004,">="&$B8,Sales!$B$5:$B$2004,"<"&EDATE($B8,1)) | E8: =SUMIFS(Sales!$K$5:$K$2004,Sales!$B$5:$B$2004,">="&$B8,Sales!$B$5:$B$2004,"<"&EDATE($B8,1)) | F8: =SUMIFS(Sales!$L$5:$L$2004,Sales!$B$5:$B$2004,">="&$B8,Sales!$B$5:$B$2004,"<"&EDATE($B8,1)) | G8: =SUMIFS(Sales!$M$5:$M$2004,Sales!$B$5:$B$2004,">="&$B8,Sales!$B$5:$B$2004,"<"&EDATE($B8,1)) | H8: =SUMIFS(Sales!$I$5:$I$2004,Sales!$B$5:$B$2004,">="&$B8,Sales!$B$5:$B$2004,"<"&EDATE($B8,1)) | I8: =SUMIFS(Expenses!$F$5:$F$2004,Expenses!$B$5:$B$2004,">="&$B8,Expenses!$B$5:$B$2004,"<"&EDATE($B8,1)) | J8: =D8-E8-F8-G8-H8-I8
B9: =EDATE(Settings!$C$6,3) | C9: =COUNTIFS(Sales!$B$5:$B$2004,">="&$B9,Sales!$B$5:$B$2004,"<"&EDATE($B9,1)) | D9: =SUMIFS(Sales!$J$5:$J$2004,Sales!$B$5:$B$2004,">="&$B9,Sales!$B$5:$B$2004,"<"&EDATE($B9,1)) | E9: =SUMIFS(Sales!$K$5:$K$2004,Sales!$B$5:$B$2004,">="&$B9,Sales!$B$5:$B$2004,"<"&EDATE($B9,1)) | F9: =SUMIFS(Sales!$L$5:$L$2004,Sales!$B$5:$B$2004,">="&$B9,Sales!$B$5:$B$2004,"<"&EDATE($B9,1)) | G9: =SUMIFS(Sales!$M$5:$M$2004,Sales!$B$5:$B$2004,">="&$B9,Sales!$B$5:$B$2004,"<"&EDATE($B9,1)) | H9: =SUMIFS(Sales!$I$5:$I$2004,Sales!$B$5:$B$2004,">="&$B9,Sales!$B$5:$B$2004,"<"&EDATE($B9,1)) | I9: =SUMIFS(Expenses!$F$5:$F$2004,Expenses!$B$5:$B$2004,">="&$B9,Expenses!$B$5:$B$2004,"<"&EDATE($B9,1)) | J9: =D9-E9-F9-G9-H9-I9
B10: =EDATE(Settings!$C$6,4) | C10: =COUNTIFS(Sales!$B$5:$B$2004,">="&$B10,Sales!$B$5:$B$2004,"<"&EDATE($B10,1)) | D10: =SUMIFS(Sales!$J$5:$J$2004,Sales!$B$5:$B$2004,">="&$B10,Sales!$B$5:$B$2004,"<"&EDATE($B10,1)) | E10: =SUMIFS(Sales!$K$5:$K$2004,Sales!$B$5:$B$2004,">="&$B10,Sales!$B$5:$B$2004,"<"&EDATE($B10,1)) | F10: =SUMIFS(Sales!$L$5:$L$2004,Sales!$B$5:$B$2004,">="&$B10,Sales!$B$5:$B$2004,"<"&EDATE($B10,1)) | G10: =SUMIFS(Sales!$M$5:$M$2004,Sales!$B$5:$B$2004,">="&$B10,Sales!$B$5:$B$2004,"<"&EDATE($B10,1)) | H10: =SUMIFS(Sales!$I$5:$I$2004,Sales!$B$5:$B$2004,">="&$B10,Sales!$B$5:$B$2004,"<"&EDATE($B10,1)) | I10: =SUMIFS(Expenses!$F$5:$F$2004,Expenses!$B$5:$B$2004,">="&$B10,Expenses!$B$5:$B$2004,"<"&EDATE($B10,1)) | J10: =D10-E10-F10-G10-H10-I10
B11: =EDATE(Settings!$C$6,5) | C11: =COUNTIFS(Sales!$B$5:$B$2004,">="&$B11,Sales!$B$5:$B$2004,"<"&EDATE($B11,1)) | D11: =SUMIFS(Sales!$J$5:$J$2004,Sales!$B$5:$B$2004,">="&$B11,Sales!$B$5:$B$2004,"<"&EDATE($B11,1)) | E11: =SUMIFS(Sales!$K$5:$K$2004,Sales!$B$5:$B$2004,">="&$B11,Sales!$B$5:$B$2004,"<"&EDATE($B11,1)) | F11: =SUMIFS(Sales!$L$5:$L$2004,Sales!$B$5:$B$2004,">="&$B11,Sales!$B$5:$B$2004,"<"&EDATE($B11,1)) | G11: =SUMIFS(Sales!$M$5:$M$2004,Sales!$B$5:$B$2004,">="&$B11,Sales!$B$5:$B$2004,"<"&EDATE($B11,1)) | H11: =SUMIFS(Sales!$I$5:$I$2004,Sales!$B$5:$B$2004,">="&$B11,Sales!$B$5:$B$2004,"<"&EDATE($B11,1)) | I11: =SUMIFS(Expenses!$F$5:$F$2004,Expenses!$B$5:$B$2004,">="&$B11,Expenses!$B$5:$B$2004,"<"&EDATE($B11,1)) | J11: =D11-E11-F11-G11-H11-I11
B12: =EDATE(Settings!$C$6,6) | C12: =COUNTIFS(Sales!$B$5:$B$2004,">="&$B12,Sales!$B$5:$B$2004,"<"&EDATE($B12,1)) | D12: =SUMIFS(Sales!$J$5:$J$2004,Sales!$B$5:$B$2004,">="&$B12,Sales!$B$5:$B$2004,"<"&EDATE($B12,1)) | E12: =SUMIFS(Sales!$K$5:$K$2004,Sales!$B$5:$B$2004,">="&$B12,Sales!$B$5:$B$2004,"<"&EDATE($B12,1)) | F12: =SUMIFS(Sales!$L$5:$L$2004,Sales!$B$5:$B$2004,">="&$B12,Sales!$B$5:$B$2004,"<"&EDATE($B12,1)) | G12: =SUMIFS(Sales!$M$5:$M$2004,Sales!$B$5:$B$2004,">="&$B12,Sales!$B$5:$B$2004,"<"&EDATE($B12,1)) | H12: =SUMIFS(Sales!$I$5:$I$2004,Sales!$B$5:$B$2004,">="&$B12,Sales!$B$5:$B$2004,"<"&EDATE($B12,1)) | I12: =SUMIFS(Expenses!$F$5:$F$2004,Expenses!$B$5:$B$2004,">="&$B12,Expenses!$B$5:$B$2004,"<"&EDATE($B12,1)) | J12: =D12-E12-F12-G12-H12-I12
B13: =EDATE(Settings!$C$6,7) | C13: =COUNTIFS(Sales!$B$5:$B$2004,">="&$B13,Sales!$B$5:$B$2004,"<"&EDATE($B13,1)) | D13: =SUMIFS(Sales!$J$5:$J$2004,Sales!$B$5:$B$2004,">="&$B13,Sales!$B$5:$B$2004,"<"&EDATE($B13,1)) | E13: =SUMIFS(Sales!$K$5:$K$2004,Sales!$B$5:$B$2004,">="&$B13,Sales!$B$5:$B$2004,"<"&EDATE($B13,1)) | F13: =SUMIFS(Sales!$L$5:$L$2004,Sales!$B$5:$B$2004,">="&$B13,Sales!$B$5:$B$2004,"<"&EDATE($B13,1)) | G13: =SUMIFS(Sales!$M$5:$M$2004,Sales!$B$5:$B$2004,">="&$B13,Sales!$B$5:$B$2004,"<"&EDATE($B13,1)) | H13: =SUMIFS(Sales!$I$5:$I$2004,Sales!$B$5:$B$2004,">="&$B13,Sales!$B$5:$B$2004,"<"&EDATE($B13,1)) | I13: =SUMIFS(Expenses!$F$5:$F$2004,Expenses!$B$5:$B$2004,">="&$B13,Expenses!$B$5:$B$2004,"<"&EDATE($B13,1)) | J13: =D13-E13-F13-G13-H13-I13
B14: =EDATE(Settings!$C$6,8) | C14: =COUNTIFS(Sales!$B$5:$B$2004,">="&$B14,Sales!$B$5:$B$2004,"<"&EDATE($B14,1)) | D14: =SUMIFS(Sales!$J$5:$J$2004,Sales!$B$5:$B$2004,">="&$B14,Sales!$B$5:$B$2004,"<"&EDATE($B14,1)) | E14: =SUMIFS(Sales!$K$5:$K$2004,Sales!$B$5:$B$2004,">="&$B14,Sales!$B$5:$B$2004,"<"&EDATE($B14,1)) | F14: =SUMIFS(Sales!$L$5:$L$2004,Sales!$B$5:$B$2004,">="&$B14,Sales!$B$5:$B$2004,"<"&EDATE($B14,1)) | G14: =SUMIFS(Sales!$M$5:$M$2004,Sales!$B$5:$B$2004,">="&$B14,Sales!$B$5:$B$2004,"<"&EDATE($B14,1)) | H14: =SUMIFS(Sales!$I$5:$I$2004,Sales!$B$5:$B$2004,">="&$B14,Sales!$B$5:$B$2004,"<"&EDATE($B14,1)) | I14: =SUMIFS(Expenses!$F$5:$F$2004,Expenses!$B$5:$B$2004,">="&$B14,Expenses!$B$5:$B$2004,"<"&EDATE($B14,1)) | J14: =D14-E14-F14-G14-H14-I14
B15: =EDATE(Settings!$C$6,9) | C15: =COUNTIFS(Sales!$B$5:$B$2004,">="&$B15,Sales!$B$5:$B$2004,"<"&EDATE($B15,1)) | D15: =SUMIFS(Sales!$J$5:$J$2004,Sales!$B$5:$B$2004,">="&$B15,Sales!$B$5:$B$2004,"<"&EDATE($B15,1)) | E15: =SUMIFS(Sales!$K$5:$K$2004,Sales!$B$5:$B$2004,">="&$B15,Sales!$B$5:$B$2004,"<"&EDATE($B15,1)) | F15: =SUMIFS(Sales!$L$5:$L$2004,Sales!$B$5:$B$2004,">="&$B15,Sales!$B$5:$B$2004,"<"&EDATE($B15,1)) | G15: =SUMIFS(Sales!$M$5:$M$2004,Sales!$B$5:$B$2004,">="&$B15,Sales!$B$5:$B$2004,"<"&EDATE($B15,1)) | H15: =SUMIFS(Sales!$I$5:$I$2004,Sales!$B$5:$B$2004,">="&$B15,Sales!$B$5:$B$2004,"<"&EDATE($B15,1)) | I15: =SUMIFS(Expenses!$F$5:$F$2004,Expenses!$B$5:$B$2004,">="&$B15,Expenses!$B$5:$B$2004,"<"&EDATE($B15,1)) | J15: =D15-E15-F15-G15-H15-I15
B16: =EDATE(Settings!$C$6,10) | C16: =COUNTIFS(Sales!$B$5:$B$2004,">="&$B16,Sales!$B$5:$B$2004,"<"&EDATE($B16,1)) | D16: =SUMIFS(Sales!$J$5:$J$2004,Sales!$B$5:$B$2004,">="&$B16,Sales!$B$5:$B$2004,"<"&EDATE($B16,1)) | E16: =SUMIFS(Sales!$K$5:$K$2004,Sales!$B$5:$B$2004,">="&$B16,Sales!$B$5:$B$2004,"<"&EDATE($B16,1)) | F16: =SUMIFS(Sales!$L$5:$L$2004,Sales!$B$5:$B$2004,">="&$B16,Sales!$B$5:$B$2004,"<"&EDATE($B16,1)) | G16: =SUMIFS(Sales!$M$5:$M$2004,Sales!$B$5:$B$2004,">="&$B16,Sales!$B$5:$B$2004,"<"&EDATE($B16,1)) | H16: =SUMIFS(Sales!$I$5:$I$2004,Sales!$B$5:$B$2004,">="&$B16,Sales!$B$5:$B$2004,"<"&EDATE($B16,1)) | I16: =SUMIFS(Expenses!$F$5:$F$2004,Expenses!$B$5:$B$2004,">="&$B16,Expenses!$B$5:$B$2004,"<"&EDATE($B16,1)) | J16: =D16-E16-F16-G16-H16-I16
B17: =EDATE(Settings!$C$6,11) | C17: =COUNTIFS(Sales!$B$5:$B$2004,">="&$B17,Sales!$B$5:$B$2004,"<"&EDATE($B17,1)) | D17: =SUMIFS(Sales!$J$5:$J$2004,Sales!$B$5:$B$2004,">="&$B17,Sales!$B$5:$B$2004,"<"&EDATE($B17,1)) | E17: =SUMIFS(Sales!$K$5:$K$2004,Sales!$B$5:$B$2004,">="&$B17,Sales!$B$5:$B$2004,"<"&EDATE($B17,1)) | F17: =SUMIFS(Sales!$L$5:$L$2004,Sales!$B$5:$B$2004,">="&$B17,Sales!$B$5:$B$2004,"<"&EDATE($B17,1)) | G17: =SUMIFS(Sales!$M$5:$M$2004,Sales!$B$5:$B$2004,">="&$B17,Sales!$B$5:$B$2004,"<"&EDATE($B17,1)) | H17: =SUMIFS(Sales!$I$5:$I$2004,Sales!$B$5:$B$2004,">="&$B17,Sales!$B$5:$B$2004,"<"&EDATE($B17,1)) | I17: =SUMIFS(Expenses!$F$5:$F$2004,Expenses!$B$5:$B$2004,">="&$B17,Expenses!$B$5:$B$2004,"<"&EDATE($B17,1)) | J17: =D17-E17-F17-G17-H17-I17
B18: Year | C18: =SUM(C6:C17) | D18: =SUM(D6:D17) | E18: =SUM(E6:E17) | F18: =SUM(F6:F17) | G18: =SUM(G6:G17) | H18: =SUM(H6:H17) | I18: =SUM(I6:I17) | J18: =SUM(J6:J17)
B21: VAT threshold check
B22: Sales in the 12 months to | C22: =Settings!C8
B23: Etsy revenue in those 12 months | C23: =SUMIFS(Sales!$J$5:$J$2004,Sales!$B$5:$B$2004,">"&EDATE(Settings!C8,-12),Sales!$B$5:$B$2004,"<="&Settings!C8)
B24: Left before the threshold | C24: =Settings!C19-C23
B25: =IF(C23>Settings!C19,"Over the VAT threshold: you must register for VAT.",IF(C24<15000,"Within £15,000 of the VAT threshold: keep a close eye on it.","Below the VAT threshold."))
B26: The threshold counts all your taxable sales, not only Etsy. Add sales from other places to be sure.
